[{"sleepStartTimestampGMT":"2022-05-11T12:59:00.0","sleepEndTimestampGMT":"2022-05-11T21:33:00.0","calendarDate":"2022-05-12","sleepWindowConfirmationType":"ENHANCED_CONFIRMED_FINAL","deepSleepSeconds":4620,"lightSleepSeconds":16020,"remSleepSeconds":8520,"awakeSleepSeconds":1680,"unmeasurableSeconds":0,"retro":false},{"sleepStartTimestampGMT":"2022-05-12T12:58:00.0","sleepEndTimestampGMT":"2022-05-12T20:48:00.0","calendarDate":"2022-05-13","sleepWindowConfirmationType":"ENHANCED_CONFIRMED_FINAL","deepSleepSeconds":5640,"lightSleepSeconds":14400,"remSleepSeconds":5520,"awakeSleepSeconds":2640,"unmeasurableSeconds":0,"retro":false},{"sleepStartTimestampGMT":"2022-05-13T13:54:00.0","sleepEndTimestampGMT":"2022-05-13T19:15:00.0","calendarDate":"2022-05-14","sleepWindowConfirmationType":"ENHANCED_CONFIRMED_FINAL","deepSleepSeconds":4920,"lightSleepSeconds":8940,"remSleepSeconds":5280,"awakeSleepSeconds":120,"unmeasurableSeconds":0,"retro":false},{"sleepStartTimestampGMT":"2022-05-14T12:59:00.0","sleepEndTimestampGMT":"2022-05-14T21:09:00.0","calendarDate":"2022-05-15","sleepWindowConfirmationType":"ENHANCED_CONFIRMED_FINAL","deepSleepSeconds":2760,"lightSleepSeconds":15300,"remSleepSeconds":8580,"awakeSleepSeconds":840,"unmeasurableSeconds":1920,"retro":false},{"sleepStartTimestampGMT":"2022-05-15T12:48:00.0","sleepEndTimestampGMT":"2022-05-15T20:05:00.0","calendarDate":"2022-05-16","sleepWindowConfirmationType":"ENHANCED_CONFIRMED_FINAL","deepSleepSeconds":4620,"lightSleepSeconds":12060,"remSleepSeconds":9480,"awakeSleepSeconds":60,"unmeasurableSeconds":0,"retro":false},{"sleepStartTimestampGMT":"2022-05-16T12:58:00.0","sleepEndTimestampGMT":"2022-05-16T21:34:00.0","calendarDate":"2022-05-17","sleepWindowConfirmationType":"ENHANCED_CONFIRMED_FINAL","deepSleepSeconds":5400,"lightSleepSeconds":15840,"remSleepSeconds":7260,"awakeSleepSeconds":2460,"unmeasurableSeconds":0,"retro":false},{"sleepStartTimestampGMT":"2022-05-17T12:49:00.0","sleepEndTimestampGMT":"2022-05-17T20:50:00.0","calendarDate":"2022-05-18","sleepWindowConfirmationType":"ENHANCED_CONFIRMED","deepSleepSeconds":5040,"lightSleepSeconds":15420,"remSleepSeconds":6480,"awakeSleepSeconds":1920,"unmeasurableSeconds":0,"retro":false},{"sleepStartTimestampGMT":"2022-05-18T13:13:00.0","sleepEndTimestampGMT":"2022-05-18T21:30:00.0","calendarDate":"2022-05-19","sleepWindowConfirmationType":"ENHANCED_CONFIRMED_FINAL","deepSleepSeconds":5820,"lightSleepSeconds":14100,"remSleepSeconds":9840,"awakeSleepSeconds":60,"unmeasurableSeconds":0,"retro":false},{"sleepStartTimestampGMT":"2022-05-19T13:46:00.0","sleepEndTimestampGMT":"2022-05-19T22:41:00.0","calendarDate":"2022-05-20","sleepWindowConfirmationType":"ENHANCED_CONFIRMED","deepSleepSeconds":4440,"lightSleepSeconds":18420,"remSleepSeconds":8820,"awakeSleepSeconds":420,"unmeasurableSeconds":0,"retro":false},{"sleepStartTimestampGMT":"2022-05-20T12:44:00.0","sleepEndTimestampGMT":"2022-05-20T20:41:00.0","calendarDate":"2022-05-21","sleepWindowConfirmationType":"ENHANCED_CONFIRMED_FINAL","deepSleepSeconds":4800,"lightSleepSeconds":14460,"remSleepSeconds":9360,"awakeSleepSeconds":0,"unmeasurableSeconds":0,"retro":false},{"sleepStartTimestampGMT":"2022-05-21T13:29:00.0","sleepEndTimestampGMT":"2022-05-21T21:46:00.0","calendarDate":"2022-05-22","sleepWindowConfirmationType":"ENHANCED_CONFIRMED_FINAL","deepSleepSeconds":3240,"lightSleepSeconds":15660,"remSleepSeconds":10020,"awakeSleepSeconds":900,"unmeasurableSeconds":0,"retro":false},{"sleepStartTimestampGMT":"2022-05-22T12:42:00.0","sleepEndTimestampGMT":"2022-05-23T00:54:00.0","calendarDate":"2022-05-23","sleepWindowConfirmationType":"AUTO_CONFIRMED_FINAL","deepSleepSeconds":35460,"lightSleepSeconds":8460,"awakeSleepSeconds":0,"unmeasurableSeconds":0,"retro":false},{"sleepStartTimestampGMT":"2022-05-23T12:57:00.0","sleepEndTimestampGMT":"2022-05-23T20:37:00.0","calendarDate":"2022-05-24","sleepWindowConfirmationType":"ENHANCED_CONFIRMED_FINAL","deepSleepSeconds":4200,"lightSleepSeconds":14760,"remSleepSeconds":8520,"awakeSleepSeconds":120,"unmeasurableSeconds":0,"retro":false},{"sleepStartTimestampGMT":"2022-05-24T13:02:00.0","sleepEndTimestampGMT":"2022-05-24T21:03:00.0","calendarDate":"2022-05-25","sleepWindowConfirmationType":"ENHANCED_CONFIRMED","deepSleepSeconds":1500,"lightSleepSeconds":15600,"remSleepSeconds":10740,"awakeSleepSeconds":1020,"unmeasurableSeconds":0,"retro":false},{"sleepStartTimestampGMT":"2022-05-25T12:44:00.0","sleepEndTimestampGMT":"2022-05-25T20:35:00.0","calendarDate":"2022-05-26","sleepWindowConfirmationType":"ENHANCED_CONFIRMED_FINAL","deepSleepSeconds":2640,"lightSleepSeconds":15480,"remSleepSeconds":10020,"awakeSleepSeconds":120,"unmeasurableSeconds":0,"retro":false},{"sleepStartTimestampGMT":"2022-05-26T13:16:00.0","sleepEndTimestampGMT":"2022-05-26T22:55:00.0","calendarDate":"2022-05-27","sleepWindowConfirmationType":"ENHANCED_CONFIRMED_FINAL","deepSleepSeconds":4680,"lightSleepSeconds":22200,"remSleepSeconds":5280,"awakeSleepSeconds":2580,"unmeasurableSeconds":0,"retro":false},{"sleepStartTimestampGMT":"2022-05-27T12:41:00.0","sleepEndTimestampGMT":"2022-05-27T21:35:00.0","calendarDate":"2022-05-28","sleepWindowConfirmationType":"ENHANCED_CONFIRMED_FINAL","deepSleepSeconds":3840,"lightSleepSeconds":17280,"remSleepSeconds":8520,"awakeSleepSeconds":2400,"unmeasurableSeconds":0,"retro":false},{"sleepStartTimestampGMT":"2022-05-28T12:36:00.0","sleepEndTimestampGMT":"2022-05-28T18:28:00.0","calendarDate":"2022-05-29","sleepWindowConfirmationType":"ENHANCED_CONFIRMED","deepSleepSeconds":2700,"lightSleepSeconds":12840,"remSleepSeconds":5580,"awakeSleepSeconds":0,"unmeasurableSeconds":0,"retro":false},{"sleepStartTimestampGMT":"2022-05-29T13:34:00.0","sleepEndTimestampGMT":"2022-05-29T21:04:00.0","calendarDate":"2022-05-30","sleepWindowConfirmationType":"ENHANCED_CONFIRMED_FINAL","deepSleepSeconds":6360,"lightSleepSeconds":11280,"remSleepSeconds":4620,"awakeSleepSeconds":4740,"unmeasurableSeconds":0,"retro":false},{"sleepStartTimestampGMT":"2022-05-30T13:22:00.0","sleepEndTimestampGMT":"2022-05-30T20:55:00.0","calendarDate":"2022-05-31","sleepWindowConfirmationType":"ENHANCED_CONFIRMED","deepSleepSeconds":3180,"lightSleepSeconds":13200,"remSleepSeconds":10740,"awakeSleepSeconds":60,"unmeasurableSeconds":0,"retro":false},{"sleepStartTimestampGMT":"2022-05-31T13:19:00.0","sleepEndTimestampGMT":"2022-05-31T19:30:00.0","calendarDate":"2022-06-01","sleepWindowConfirmationType":"ENHANCED_CONFIRMED","deepSleepSeconds":3780,"lightSleepSeconds":12060,"remSleepSeconds":6360,"awakeSleepSeconds":60,"unmeasurableSeconds":0,"retro":false},{"sleepStartTimestampGMT":"2022-06-01T13:04:00.0","sleepEndTimestampGMT":"2022-06-01T19:26:00.0","calendarDate":"2022-06-02","sleepWindowConfirmationType":"ENHANCED_CONFIRMED_FINAL","deepSleepSeconds":6300,"lightSleepSeconds":10680,"remSleepSeconds":5940,"awakeSleepSeconds":0,"unmeasurableSeconds":0,"retro":false},{"sleepStartTimestampGMT":"2022-06-02T12:52:00.0","sleepEndTimestampGMT":"2022-06-02T20:43:00.0","calendarDate":"2022-06-03","sleepWindowConfirmationType":"ENHANCED_CONFIRMED","deepSleepSeconds":3900,"lightSleepSeconds":15600,"remSleepSeconds":8160,"awakeSleepSeconds":600,"unmeasurableSeconds":0,"retro":false},{"sleepStartTimestampGMT":"2022-06-03T13:58:00.0","sleepEndTimestampGMT":"2022-06-03T21:10:00.0","calendarDate":"2022-06-04","sleepWindowConfirmationType":"ENHANCED_CONFIRMED_FINAL","deepSleepSeconds":3060,"lightSleepSeconds":15240,"remSleepSeconds":6840,"awakeSleepSeconds":780,"unmeasurableSeconds":0,"retro":false},{"sleepStartTimestampGMT":"2022-06-04T13:26:00.0","sleepEndTimestampGMT":"2022-06-04T22:01:00.0","calendarDate":"2022-06-05","sleepWindowConfirmationType":"ENHANCED_CONFIRMED_FINAL","deepSleepSeconds":4260,"lightSleepSeconds":18780,"remSleepSeconds":6060,"awakeSleepSeconds":1800,"unmeasurableSeconds":0,"retro":false},{"sleepStartTimestampGMT":"2022-06-05T12:33:00.0","sleepEndTimestampGMT":"2022-06-05T20:57:00.0","calendarDate":"2022-06-06","sleepWindowConfirmationType":"ENHANCED_CONFIRMED_FINAL","deepSleepSeconds":5820,"lightSleepSeconds":13260,"remSleepSeconds":10260,"awakeSleepSeconds":900,"unmeasurableSeconds":0,"retro":false},{"sleepStartTimestampGMT":"2022-06-06T13:36:00.0","sleepEndTimestampGMT":"2022-06-06T21:35:00.0","calendarDate":"2022-06-07","sleepWindowConfirmationType":"ENHANCED_CONFIRMED","deepSleepSeconds":5220,"lightSleepSeconds":16200,"remSleepSeconds":6180,"awakeSleepSeconds":1140,"unmeasurableSeconds":0,"retro":false},{"sleepStartTimestampGMT":"2022-06-07T12:47:00.0","sleepEndTimestampGMT":"2022-06-07T21:32:00.0","calendarDate":"2022-06-08","sleepWindowConfirmationType":"ENHANCED_CONFIRMED_FINAL","deepSleepSeconds":4980,"lightSleepSeconds":17340,"remSleepSeconds":6120,"awakeSleepSeconds":3060,"unmeasurableSeconds":0,"retro":false},{"sleepStartTimestampGMT":"2022-06-08T12:57:00.0","sleepEndTimestampGMT":"2022-06-08T20:44:00.0","calendarDate":"2022-06-09","sleepWindowConfirmationType":"ENHANCED_CONFIRMED","deepSleepSeconds":6420,"lightSleepSeconds":11340,"remSleepSeconds":10260,"awakeSleepSeconds":0,"unmeasurableSeconds":0,"retro":false},{"sleepStartTimestampGMT":"2022-06-09T12:28:00.0","sleepEndTimestampGMT":"2022-06-09T21:26:00.0","calendarDate":"2022-06-10","sleepWindowConfirmationType":"ENHANCED_CONFIRMED","deepSleepSeconds":4860,"lightSleepSeconds":15960,"remSleepSeconds":11340,"awakeSleepSeconds":120,"unmeasurableSeconds":0,"retro":false},{"sleepStartTimestampGMT":"2022-06-10T13:51:00.0","sleepEndTimestampGMT":"2022-06-10T20:34:00.0","calendarDate":"2022-06-11","sleepWindowConfirmationType":"ENHANCED_CONFIRMED_FINAL","deepSleepSeconds":1260,"lightSleepSeconds":14280,"remSleepSeconds":8640,"awakeSleepSeconds":0,"unmeasurableSeconds":0,"retro":false},{"sleepStartTimestampGMT":"2022-06-11T12:59:00.0","sleepEndTimestampGMT":"2022-06-11T20:43:00.0","calendarDate":"2022-06-12","sleepWindowConfirmationType":"ENHANCED_CONFIRMED_FINAL","deepSleepSeconds":3720,"lightSleepSeconds":14580,"remSleepSeconds":9540,"awakeSleepSeconds":0,"unmeasurableSeconds":0,"retro":false},{"sleepStartTimestampGMT":"2022-06-12T13:53:00.0","sleepEndTimestampGMT":"2022-06-12T22:09:00.0","calendarDate":"2022-06-13","sleepWindowConfirmationType":"ENHANCED_CONFIRMED","deepSleepSeconds":3000,"lightSleepSeconds":17040,"remSleepSeconds":8100,"awakeSleepSeconds":1620,"unmeasurableSeconds":0,"retro":false},{"sleepStartTimestampGMT":"2022-06-13T12:32:00.0","sleepEndTimestampGMT":"2022-06-13T21:24:00.0","calendarDate":"2022-06-14","sleepWindowConfirmationType":"ENHANCED_CONFIRMED_FINAL","deepSleepSeconds":4140,"lightSleepSeconds":15660,"remSleepSeconds":12000,"awakeSleepSeconds":120,"unmeasurableSeconds":0,"retro":false},{"sleepStartTimestampGMT":"2022-06-14T13:49:00.0","sleepEndTimestampGMT":"2022-06-14T21:29:00.0","calendarDate":"2022-06-15","sleepWindowConfirmationType":"ENHANCED_CONFIRMED","deepSleepSeconds":3240,"lightSleepSeconds":13800,"remSleepSeconds":9840,"awakeSleepSeconds":720,"unmeasurableSeconds":0,"retro":false},{"sleepStartTimestampGMT":"2022-06-15T12:54:00.0","sleepEndTimestampGMT":"2022-06-15T20:45:00.0","calendarDate":"2022-06-16","sleepWindowConfirmationType":"ENHANCED_CONFIRMED_FINAL","deepSleepSeconds":3540,"lightSleepSeconds":14580,"remSleepSeconds":10140,"awakeSleepSeconds":0,"unmeasurableSeconds":0,"retro":false},{"sleepStartTimestampGMT":"2022-06-16T12:59:00.0","sleepEndTimestampGMT":"2022-06-16T21:45:00.0","calendarDate":"2022-06-17","sleepWindowConfirmationType":"ENHANCED_CONFIRMED","deepSleepSeconds":4620,"lightSleepSeconds":17100,"remSleepSeconds":4320,"awakeSleepSeconds":5520,"unmeasurableSeconds":0,"retro":false},{"sleepStartTimestampGMT":"2022-06-17T13:58:00.0","sleepEndTimestampGMT":"2022-06-17T21:05:00.0","calendarDate":"2022-06-18","sleepWindowConfirmationType":"ENHANCED_CONFIRMED_FINAL","deepSleepSeconds":4020,"lightSleepSeconds":12180,"remSleepSeconds":9300,"awakeSleepSeconds":120,"unmeasurableSeconds":0,"retro":false},{"sleepStartTimestampGMT":"2022-06-18T13:09:00.0","sleepEndTimestampGMT":"2022-06-18T20:44:00.0","calendarDate":"2022-06-19","sleepWindowConfirmationType":"ENHANCED_CONFIRMED_FINAL","deepSleepSeconds":5580,"lightSleepSeconds":13680,"remSleepSeconds":6540,"awakeSleepSeconds":360,"unmeasurableSeconds":1140,"retro":false},{"sleepStartTimestampGMT":"2022-06-19T12:54:00.0","sleepEndTimestampGMT":"2022-06-20T00:59:00.0","calendarDate":"2022-06-20","sleepWindowConfirmationType":"AUTO_CONFIRMED_FINAL","deepSleepSeconds":18180,"lightSleepSeconds":25140,"awakeSleepSeconds":180,"unmeasurableSeconds":0,"retro":false},{"sleepStartTimestampGMT":"2022-06-20T13:16:00.0","sleepEndTimestampGMT":"2022-06-20T21:18:00.0","calendarDate":"2022-06-21","sleepWindowConfirmationType":"ENHANCED_CONFIRMED_FINAL","deepSleepSeconds":3540,"lightSleepSeconds":16020,"remSleepSeconds":8520,"awakeSleepSeconds":840,"unmeasurableSeconds":0,"retro":false},{"sleepStartTimestampGMT":"2022-06-21T12:03:00.0","sleepEndTimestampGMT":"2022-06-21T21:20:00.0","calendarDate":"2022-06-22","sleepWindowConfirmationType":"ENHANCED_CONFIRMED","deepSleepSeconds":1800,"lightSleepSeconds":22200,"remSleepSeconds":4320,"awakeSleepSeconds":2880,"unmeasurableSeconds":2220,"retro":false},{"sleepStartTimestampGMT":"2022-06-22T12:02:00.0","sleepEndTimestampGMT":"2022-06-22T20:46:00.0","calendarDate":"2022-06-23","sleepWindowConfirmationType":"ENHANCED_CONFIRMED","deepSleepSeconds":6240,"lightSleepSeconds":15360,"remSleepSeconds":9780,"awakeSleepSeconds":60,"unmeasurableSeconds":0,"retro":false},{"sleepStartTimestampGMT":"2022-06-23T13:26:00.0","sleepEndTimestampGMT":"2022-06-23T19:36:00.0","calendarDate":"2022-06-24","sleepWindowConfirmationType":"ENHANCED_CONFIRMED_FINAL","deepSleepSeconds":5340,"lightSleepSeconds":11400,"remSleepSeconds":4800,"awakeSleepSeconds":660,"unmeasurableSeconds":0,"retro":false},{"sleepStartTimestampGMT":"2022-06-24T13:04:00.0","sleepEndTimestampGMT":"2022-06-24T21:39:00.0","calendarDate":"2022-06-25","sleepWindowConfirmationType":"ENHANCED_CONFIRMED_FINAL","deepSleepSeconds":2820,"lightSleepSeconds":16680,"remSleepSeconds":10740,"awakeSleepSeconds":660,"unmeasurableSeconds":0,"retro":false},{"sleepStartTimestampGMT":"2022-06-25T12:49:00.0","sleepEndTimestampGMT":"2022-06-25T22:12:00.0","calendarDate":"2022-06-26","sleepWindowConfirmationType":"ENHANCED_CONFIRMED_FINAL","deepSleepSeconds":3180,"lightSleepSeconds":15060,"remSleepSeconds":12780,"awakeSleepSeconds":960,"unmeasurableSeconds":1800,"retro":false},{"sleepStartTimestampGMT":"2022-06-26T12:50:00.0","sleepEndTimestampGMT":"2022-06-26T21:16:00.0","calendarDate":"2022-06-27","sleepWindowConfirmationType":"ENHANCED_CONFIRMED_FINAL","deepSleepSeconds":3600,"lightSleepSeconds":19020,"remSleepSeconds":6960,"awakeSleepSeconds":780,"unmeasurableSeconds":0,"retro":false},{"sleepStartTimestampGMT":"2022-06-27T12:40:00.0","sleepEndTimestampGMT":"2022-06-27T20:49:00.0","calendarDate":"2022-06-28","sleepWindowConfirmationType":"ENHANCED_CONFIRMED","deepSleepSeconds":3960,"lightSleepSeconds":15600,"remSleepSeconds":9660,"awakeSleepSeconds":120,"unmeasurableSeconds":0,"retro":false},{"sleepStartTimestampGMT":"2022-06-28T12:31:00.0","sleepEndTimestampGMT":"2022-06-28T21:30:00.0","calendarDate":"2022-06-29","sleepWindowConfirmationType":"ENHANCED_CONFIRMED_FINAL","deepSleepSeconds":5820,"lightSleepSeconds":14940,"remSleepSeconds":10920,"awakeSleepSeconds":660,"unmeasurableSeconds":0,"retro":false},{"sleepStartTimestampGMT":"2022-06-29T13:30:00.0","sleepEndTimestampGMT":"2022-06-29T20:00:00.0","calendarDate":"2022-06-30","sleepWindowConfirmationType":"ENHANCED_CONFIRMED","deepSleepSeconds":3000,"lightSleepSeconds":12360,"remSleepSeconds":7380,"awakeSleepSeconds":660,"unmeasurableSeconds":0,"retro":false},{"sleepStartTimestampGMT":"2022-06-30T18:28:00.0","sleepEndTimestampGMT":"2022-06-30T23:15:00.0","calendarDate":"2022-07-01","sleepWindowConfirmationType":"OFF_WRIST","deepSleepSeconds":0,"lightSleepSeconds":0,"awakeSleepSeconds":0,"unmeasurableSeconds":0,"retro":false},{"sleepStartTimestampGMT":"2022-07-01T14:51:00.0","sleepEndTimestampGMT":"2022-07-01T21:34:00.0","calendarDate":"2022-07-02","sleepWindowConfirmationType":"ENHANCED_CONFIRMED_FINAL","deepSleepSeconds":5400,"lightSleepSeconds":15180,"remSleepSeconds":2220,"awakeSleepSeconds":1380,"unmeasurableSeconds":0,"retro":false},{"sleepStartTimestampGMT":"2022-07-02T12:42:00.0","sleepEndTimestampGMT":"2022-07-02T21:03:00.0","calendarDate":"2022-07-03","sleepWindowConfirmationType":"ENHANCED_CONFIRMED_FINAL","deepSleepSeconds":5040,"lightSleepSeconds":13560,"remSleepSeconds":11460,"awakeSleepSeconds":0,"unmeasurableSeconds":0,"retro":false},{"sleepStartTimestampGMT":"2022-07-03T12:27:00.0","sleepEndTimestampGMT":"2022-07-03T20:47:00.0","calendarDate":"2022-07-04","sleepWindowConfirmationType":"ENHANCED_CONFIRMED_FINAL","deepSleepSeconds":5700,"lightSleepSeconds":15240,"remSleepSeconds":7440,"awakeSleepSeconds":1620,"unmeasurableSeconds":0,"retro":false},{"sleepStartTimestampGMT":"2022-07-04T13:09:00.0","sleepEndTimestampGMT":"2022-07-04T20:56:00.0","calendarDate":"2022-07-05","sleepWindowConfirmationType":"ENHANCED_CONFIRMED","deepSleepSeconds":4080,"lightSleepSeconds":12180,"remSleepSeconds":11760,"awakeSleepSeconds":0,"unmeasurableSeconds":0,"retro":false},{"sleepStartTimestampGMT":"2022-07-05T12:33:00.0","sleepEndTimestampGMT":"2022-07-05T21:10:00.0","calendarDate":"2022-07-06","sleepWindowConfirmationType":"ENHANCED_CONFIRMED","deepSleepSeconds":5580,"lightSleepSeconds":14820,"remSleepSeconds":6300,"awakeSleepSeconds":2340,"unmeasurableSeconds":1980,"retro":false},{"sleepStartTimestampGMT":"2022-07-06T12:38:00.0","sleepEndTimestampGMT":"2022-07-06T19:37:00.0","calendarDate":"2022-07-07","sleepWindowConfirmationType":"ENHANCED_CONFIRMED_FINAL","deepSleepSeconds":1500,"lightSleepSeconds":13200,"remSleepSeconds":10320,"awakeSleepSeconds":120,"unmeasurableSeconds":0,"retro":false},{"sleepStartTimestampGMT":"2022-07-07T13:43:00.0","sleepEndTimestampGMT":"2022-07-07T21:15:00.0","calendarDate":"2022-07-08","sleepWindowConfirmationType":"ENHANCED_CONFIRMED","deepSleepSeconds":5100,"lightSleepSeconds":11280,"remSleepSeconds":5760,"awakeSleepSeconds":3720,"unmeasurableSeconds":1260,"retro":false},{"sleepStartTimestampGMT":"2022-07-08T12:26:00.0","sleepEndTimestampGMT":"2022-07-08T19:49:00.0","calendarDate":"2022-07-09","sleepWindowConfirmationType":"ENHANCED_CONFIRMED_FINAL","deepSleepSeconds":5040,"lightSleepSeconds":12060,"remSleepSeconds":9480,"awakeSleepSeconds":0,"unmeasurableSeconds":0,"retro":false},{"sleepStartTimestampGMT":"2022-07-09T13:27:00.0","sleepEndTimestampGMT":"2022-07-09T21:30:00.0","calendarDate":"2022-07-10","sleepWindowConfirmationType":"ENHANCED_CONFIRMED_FINAL","deepSleepSeconds":4800,"lightSleepSeconds":20460,"remSleepSeconds":3120,"awakeSleepSeconds":600,"unmeasurableSeconds":0,"retro":false},{"sleepStartTimestampGMT":"2022-07-10T12:37:00.0","sleepEndTimestampGMT":"2022-07-10T21:03:00.0","calendarDate":"2022-07-11","sleepWindowConfirmationType":"ENHANCED_CONFIRMED","deepSleepSeconds":6000,"lightSleepSeconds":13380,"remSleepSeconds":8160,"awakeSleepSeconds":540,"unmeasurableSeconds":2280,"retro":false},{"sleepStartTimestampGMT":"2022-07-11T12:19:00.0","sleepEndTimestampGMT":"2022-07-11T17:12:00.0","calendarDate":"2022-07-12","sleepWindowConfirmationType":"ENHANCED_CONFIRMED","deepSleepSeconds":5160,"lightSleepSeconds":8220,"remSleepSeconds":4200,"awakeSleepSeconds":0,"unmeasurableSeconds":0,"retro":false},{"sleepStartTimestampGMT":"2022-07-12T12:38:00.0","sleepEndTimestampGMT":"2022-07-12T19:46:00.0","calendarDate":"2022-07-13","sleepWindowConfirmationType":"AUTO_CONFIRMED_FINAL","deepSleepSeconds":16680,"lightSleepSeconds":8280,"awakeSleepSeconds":720,"unmeasurableSeconds":0,"retro":false},{"sleepStartTimestampGMT":"2022-07-13T12:54:00.0","sleepEndTimestampGMT":"2022-07-13T20:36:00.0","calendarDate":"2022-07-14","sleepWindowConfirmationType":"ENHANCED_CONFIRMED_FINAL","deepSleepSeconds":7680,"lightSleepSeconds":9180,"remSleepSeconds":6900,"awakeSleepSeconds":3960,"unmeasurableSeconds":0,"retro":false},{"sleepStartTimestampGMT":"2022-07-14T12:30:00.0","sleepEndTimestampGMT":"2022-07-14T20:57:00.0","calendarDate":"2022-07-15","sleepWindowConfirmationType":"ENHANCED_CONFIRMED","deepSleepSeconds":1440,"lightSleepSeconds":16260,"remSleepSeconds":10440,"awakeSleepSeconds":300,"unmeasurableSeconds":1980,"retro":false},{"sleepStartTimestampGMT":"2022-07-15T13:32:00.0","sleepEndTimestampGMT":"2022-07-15T20:35:00.0","calendarDate":"2022-07-16","sleepWindowConfirmationType":"ENHANCED_CONFIRMED_FINAL","deepSleepSeconds":3480,"lightSleepSeconds":14400,"remSleepSeconds":7200,"awakeSleepSeconds":300,"unmeasurableSeconds":0,"retro":false},{"sleepStartTimestampGMT":"2022-07-16T12:12:00.0","sleepEndTimestampGMT":"2022-07-16T21:18:00.0","calendarDate":"2022-07-17","sleepWindowConfirmationType":"ENHANCED_CONFIRMED_FINAL","deepSleepSeconds":3480,"lightSleepSeconds":18960,"remSleepSeconds":9840,"awakeSleepSeconds":480,"unmeasurableSeconds":0,"retro":false},{"sleepStartTimestampGMT":"2022-07-17T12:30:00.0","sleepEndTimestampGMT":"2022-07-17T20:45:00.0","calendarDate":"2022-07-18","sleepWindowConfirmationType":"ENHANCED_CONFIRMED_FINAL","deepSleepSeconds":5040,"lightSleepSeconds":14520,"remSleepSeconds":7680,"awakeSleepSeconds":1140,"unmeasurableSeconds":1320,"retro":false},{"sleepStartTimestampGMT":"2022-07-18T11:17:00.0","sleepEndTimestampGMT":"2022-07-18T21:21:00.0","calendarDate":"2022-07-19","sleepWindowConfirmationType":"OFF_WRIST","deepSleepSeconds":0,"lightSleepSeconds":0,"awakeSleepSeconds":0,"unmeasurableSeconds":0,"retro":false},{"sleepStartTimestampGMT":"2022-07-19T13:16:00.0","sleepEndTimestampGMT":"2022-07-19T21:13:00.0","calendarDate":"2022-07-20","sleepWindowConfirmationType":"ENHANCED_CONFIRMED","deepSleepSeconds":3480,"lightSleepSeconds":16500,"remSleepSeconds":5400,"awakeSleepSeconds":2220,"unmeasurableSeconds":1020,"retro":false},{"sleepStartTimestampGMT":"2022-07-20T13:00:00.0","sleepEndTimestampGMT":"2022-07-20T20:29:00.0","calendarDate":"2022-07-21","sleepWindowConfirmationType":"ENHANCED_CONFIRMED_FINAL","deepSleepSeconds":2220,"lightSleepSeconds":14160,"remSleepSeconds":9780,"awakeSleepSeconds":0,"unmeasurableSeconds":780,"retro":false},{"sleepStartTimestampGMT":"2022-07-21T12:51:00.0","sleepEndTimestampGMT":"2022-07-21T17:53:00.0","calendarDate":"2022-07-22","sleepWindowConfirmationType":"ENHANCED_CONFIRMED","deepSleepSeconds":3840,"lightSleepSeconds":9540,"remSleepSeconds":4680,"awakeSleepSeconds":60,"unmeasurableSeconds":0,"retro":false},{"sleepStartTimestampGMT":"2022-07-22T12:30:00.0","sleepEndTimestampGMT":"2022-07-22T21:32:00.0","calendarDate":"2022-07-23","sleepWindowConfirmationType":"ENHANCED_CONFIRMED_FINAL","deepSleepSeconds":6000,"lightSleepSeconds":17460,"remSleepSeconds":8220,"awakeSleepSeconds":840,"unmeasurableSeconds":0,"retro":false},{"sleepStartTimestampGMT":"2022-07-23T12:21:00.0","sleepEndTimestampGMT":"2022-07-23T19:50:00.0","calendarDate":"2022-07-24","sleepWindowConfirmationType":"ENHANCED_CONFIRMED_FINAL","deepSleepSeconds":3780,"lightSleepSeconds":13920,"remSleepSeconds":9120,"awakeSleepSeconds":120,"unmeasurableSeconds":0,"retro":false},{"sleepStartTimestampGMT":"2022-07-24T14:08:00.0","sleepEndTimestampGMT":"2022-07-24T21:06:00.0","calendarDate":"2022-07-25","sleepWindowConfirmationType":"ENHANCED_CONFIRMED","deepSleepSeconds":3120,"lightSleepSeconds":12840,"remSleepSeconds":8160,"awakeSleepSeconds":960,"unmeasurableSeconds":0,"retro":false},{"sleepStartTimestampGMT":"2022-07-25T12:49:00.0","sleepEndTimestampGMT":"2022-07-25T22:00:00.0","calendarDate":"2022-07-26","sleepWindowConfirmationType":"ENHANCED_CONFIRMED","deepSleepSeconds":2160,"lightSleepSeconds":18960,"remSleepSeconds":10020,"awakeSleepSeconds":1920,"unmeasurableSeconds":0,"retro":false},{"sleepStartTimestampGMT":"2022-07-26T12:28:00.0","sleepEndTimestampGMT":"2022-07-26T20:28:00.0","calendarDate":"2022-07-27","sleepWindowConfirmationType":"ENHANCED_CONFIRMED_FINAL","deepSleepSeconds":5340,"lightSleepSeconds":17340,"remSleepSeconds":6120,"awakeSleepSeconds":0,"unmeasurableSeconds":0,"retro":false},{"sleepStartTimestampGMT":"2022-07-27T12:49:00.0","sleepEndTimestampGMT":"2022-07-27T20:40:00.0","calendarDate":"2022-07-28","sleepWindowConfirmationType":"ENHANCED_CONFIRMED_FINAL","deepSleepSeconds":3240,"lightSleepSeconds":15780,"remSleepSeconds":7920,"awakeSleepSeconds":1320,"unmeasurableSeconds":0,"retro":false},{"sleepStartTimestampGMT":"2022-07-28T12:47:00.0","sleepEndTimestampGMT":"2022-07-28T20:39:00.0","calendarDate":"2022-07-29","sleepWindowConfirmationType":"ENHANCED_CONFIRMED","deepSleepSeconds":2100,"lightSleepSeconds":17040,"remSleepSeconds":9060,"awakeSleepSeconds":120,"unmeasurableSeconds":0,"retro":false},{"sleepStartTimestampGMT":"2022-07-29T12:47:00.0","sleepEndTimestampGMT":"2022-07-29T20:33:00.0","calendarDate":"2022-07-30","sleepWindowConfirmationType":"ENHANCED_CONFIRMED_FINAL","deepSleepSeconds":3960,"lightSleepSeconds":14220,"remSleepSeconds":8280,"awakeSleepSeconds":1500,"unmeasurableSeconds":0,"retro":false},{"sleepStartTimestampGMT":"2022-07-30T13:11:00.0","sleepEndTimestampGMT":"2022-07-30T21:34:00.0","calendarDate":"2022-07-31","sleepWindowConfirmationType":"ENHANCED_CONFIRMED_FINAL","deepSleepSeconds":6120,"lightSleepSeconds":16800,"remSleepSeconds":6720,"awakeSleepSeconds":540,"unmeasurableSeconds":0,"retro":false},{"sleepStartTimestampGMT":"2022-07-31T13:06:00.0","sleepEndTimestampGMT":"2022-07-31T21:15:00.0","calendarDate":"2022-08-01","sleepWindowConfirmationType":"ENHANCED_CONFIRMED_FINAL","deepSleepSeconds":6180,"lightSleepSeconds":13500,"remSleepSeconds":4500,"awakeSleepSeconds":5160,"unmeasurableSeconds":0,"retro":false},{"sleepStartTimestampGMT":"2022-08-01T12:27:00.0","sleepEndTimestampGMT":"2022-08-01T21:16:00.0","calendarDate":"2022-08-02","sleepWindowConfirmationType":"ENHANCED_CONFIRMED","deepSleepSeconds":5400,"lightSleepSeconds":17280,"remSleepSeconds":8400,"awakeSleepSeconds":660,"unmeasurableSeconds":0,"retro":false},{"sleepStartTimestampGMT":"2022-08-02T12:35:00.0","sleepEndTimestampGMT":"2022-08-02T21:01:00.0","calendarDate":"2022-08-03","sleepWindowConfirmationType":"ENHANCED_CONFIRMED","deepSleepSeconds":3600,"lightSleepSeconds":16920,"remSleepSeconds":9120,"awakeSleepSeconds":720,"unmeasurableSeconds":0,"retro":false},{"sleepStartTimestampGMT":"2022-08-03T12:39:00.0","sleepEndTimestampGMT":"2022-08-03T20:09:00.0","calendarDate":"2022-08-04","sleepWindowConfirmationType":"ENHANCED_CONFIRMED_FINAL","deepSleepSeconds":2820,"lightSleepSeconds":16680,"remSleepSeconds":6960,"awakeSleepSeconds":540,"unmeasurableSeconds":0,"retro":false},{"sleepStartTimestampGMT":"2022-08-04T12:58:00.0","sleepEndTimestampGMT":"2022-08-04T20:13:00.0","calendarDate":"2022-08-05","sleepWindowConfirmationType":"ENHANCED_CONFIRMED_FINAL","deepSleepSeconds":4140,"lightSleepSeconds":12060,"remSleepSeconds":7320,"awakeSleepSeconds":2580,"unmeasurableSeconds":0,"retro":false},{"sleepStartTimestampGMT":"2022-08-05T13:05:00.0","sleepEndTimestampGMT":"2022-08-05T18:59:00.0","calendarDate":"2022-08-06","sleepWindowConfirmationType":"ENHANCED_CONFIRMED","deepSleepSeconds":4320,"lightSleepSeconds":8580,"remSleepSeconds":8280,"awakeSleepSeconds":60,"unmeasurableSeconds":0,"retro":false},{"sleepStartTimestampGMT":"2022-08-06T12:00:00.0","sleepEndTimestampGMT":"2022-08-06T21:42:00.0","calendarDate":"2022-08-07","sleepWindowConfirmationType":"ENHANCED_CONFIRMED_FINAL","deepSleepSeconds":3900,"lightSleepSeconds":18960,"remSleepSeconds":9660,"awakeSleepSeconds":2400,"unmeasurableSeconds":0,"retro":false},{"sleepStartTimestampGMT":"2022-08-07T12:34:00.0","sleepEndTimestampGMT":"2022-08-07T20:18:00.0","calendarDate":"2022-08-08","sleepWindowConfirmationType":"ENHANCED_CONFIRMED","deepSleepSeconds":4260,"lightSleepSeconds":12660,"remSleepSeconds":10440,"awakeSleepSeconds":480,"unmeasurableSeconds":0,"retro":false},{"sleepStartTimestampGMT":"2022-08-08T12:17:00.0","sleepEndTimestampGMT":"2022-08-08T20:39:00.0","calendarDate":"2022-08-09","sleepWindowConfirmationType":"ENHANCED_CONFIRMED_FINAL","deepSleepSeconds":5580,"lightSleepSeconds":15540,"remSleepSeconds":6480,"awakeSleepSeconds":2520,"unmeasurableSeconds":0,"retro":false},{"sleepStartTimestampGMT":"2022-08-09T12:49:00.0","sleepEndTimestampGMT":"2022-08-09T19:42:00.0","calendarDate":"2022-08-10","sleepWindowConfirmationType":"ENHANCED_CONFIRMED_FINAL","deepSleepSeconds":3300,"lightSleepSeconds":14580,"remSleepSeconds":6060,"awakeSleepSeconds":840,"unmeasurableSeconds":0,"retro":false},{"sleepStartTimestampGMT":"2022-08-10T12:53:00.0","sleepEndTimestampGMT":"2022-08-10T20:34:00.0","calendarDate":"2022-08-11","sleepWindowConfirmationType":"ENHANCED_CONFIRMED","deepSleepSeconds":3180,"lightSleepSeconds":15180,"remSleepSeconds":8940,"awakeSleepSeconds":360,"unmeasurableSeconds":0,"retro":false},{"sleepStartTimestampGMT":"2022-08-11T12:40:00.0","sleepEndTimestampGMT":"2022-08-11T20:48:00.0","calendarDate":"2022-08-12","sleepWindowConfirmationType":"ENHANCED_CONFIRMED","deepSleepSeconds":2700,"lightSleepSeconds":15180,"remSleepSeconds":11100,"awakeSleepSeconds":240,"unmeasurableSeconds":0,"averageRespiration":13.0,"lowestRespiration":9.0,"highestRespiration":16.0,"retro":false},{"sleepStartTimestampGMT":"2022-08-12T13:22:00.0","sleepEndTimestampGMT":"2022-08-12T19:49:00.0","calendarDate":"2022-08-13","sleepWindowConfirmationType":"ENHANCED_CONFIRMED","deepSleepSeconds":4500,"lightSleepSeconds":11520,"remSleepSeconds":6000,"awakeSleepSeconds":1200,"unmeasurableSeconds":0,"averageRespiration":13.0,"lowestRespiration":9.0,"highestRespiration":16.0,"retro":false},{"sleepStartTimestampGMT":"2022-08-13T15:09:00.0","sleepEndTimestampGMT":"2022-08-14T00:09:00.0","calendarDate":"2022-08-14","sleepWindowConfirmationType":"ENHANCED_CONFIRMED","deepSleepSeconds":1800,"lightSleepSeconds":26400,"remSleepSeconds":3180,"awakeSleepSeconds":1020,"unmeasurableSeconds":0,"averageRespiration":14.0,"lowestRespiration":10.0,"highestRespiration":20.0,"retro":false},{"sleepStartTimestampGMT":"2022-08-14T12:29:00.0","sleepEndTimestampGMT":"2022-08-14T21:43:00.0","calendarDate":"2022-08-15","sleepWindowConfirmationType":"ENHANCED_CONFIRMED","deepSleepSeconds":2940,"lightSleepSeconds":20280,"remSleepSeconds":9840,"awakeSleepSeconds":180,"unmeasurableSeconds":0,"averageRespiration":13.0,"lowestRespiration":7.0,"highestRespiration":16.0,"retro":false},{"sleepStartTimestampGMT":"2022-08-15T12:03:00.0","sleepEndTimestampGMT":"2022-08-15T21:12:00.0","calendarDate":"2022-08-16","sleepWindowConfirmationType":"ENHANCED_CONFIRMED","deepSleepSeconds":4560,"lightSleepSeconds":18960,"remSleepSeconds":5280,"awakeSleepSeconds":4140,"unmeasurableSeconds":0,"averageRespiration":13.0,"lowestRespiration":10.0,"highestRespiration":15.0,"retro":false},{"sleepStartTimestampGMT":"2022-08-16T12:33:00.0","sleepEndTimestampGMT":"2022-08-16T20:50:00.0","calendarDate":"2022-08-17","sleepWindowConfirmationType":"ENHANCED_CONFIRMED","deepSleepSeconds":7860,"lightSleepSeconds":14700,"remSleepSeconds":7140,"awakeSleepSeconds":120,"unmeasurableSeconds":0,"averageRespiration":12.0,"lowestRespiration":6.0,"highestRespiration":16.0,"retro":false},{"sleepStartTimestampGMT":"2022-08-17T12:41:00.0","sleepEndTimestampGMT":"2022-08-17T21:17:00.0","calendarDate":"2022-08-18","sleepWindowConfirmationType":"ENHANCED_CONFIRMED","deepSleepSeconds":6540,"lightSleepSeconds":16560,"remSleepSeconds":6900,"awakeSleepSeconds":960,"unmeasurableSeconds":0,"averageRespiration":12.0,"lowestRespiration":9.0,"highestRespiration":16.0,"retro":false},{"sleepStartTimestampGMT":"2022-08-18T12:04:00.0","sleepEndTimestampGMT":"2022-08-18T21:21:00.0","calendarDate":"2022-08-19","sleepWindowConfirmationType":"ENHANCED_CONFIRMED","deepSleepSeconds":2340,"lightSleepSeconds":21840,"remSleepSeconds":8520,"awakeSleepSeconds":720,"unmeasurableSeconds":0,"averageRespiration":12.0,"lowestRespiration":7.0,"highestRespiration":17.0,"retro":false}]